setup.py
src/limecc/__init__.py
src/limecc/fa.py
src/limecc/first.py
src/limecc/grammar.py
src/limecc/lime_cpp.py
src/limecc/lime_grammar.py
src/limecc/limecc.py
src/limecc/lrparser.py
src/limecc/regex_parser.py
src/limecc/rule.py
src/limecc.egg-info/PKG-INFO
src/limecc.egg-info/SOURCES.txt
src/limecc.egg-info/dependency_links.txt
src/limecc.egg-info/entry_points.txt
src/limecc.egg-info/requires.txt
src/limecc.egg-info/top_level.txt