Metadata-Version: 1.0
Name: limecc
Version: 0.2
Summary: Lexer and parser generator with a lemon-like description language
Home-page: http://github.com/avakar/limecc
Author: Martin Vejnár
Author-email: avakar@ratatanek.cz
License: Boost
Platform: UNKNOWN
